faultdiagnosistoolbox-0.12.5.dist-info/METADATA
faultdiagnosistoolbox-0.12.5.dist-info/RECORD
faultdiagnosistoolbox-0.12.5.dist-info/WHEEL
faultdiagnosistoolbox-0.12.5.dist-info/licenses/LICENSE
faultdiagnosistoolbox/DiagnosisModel.py
faultdiagnosistoolbox/SensorPlacement.py
faultdiagnosistoolbox/__init__.py
faultdiagnosistoolbox/_version.py
faultdiagnosistoolbox/MHS.py
faultdiagnosistoolbox/TestSelection.py
faultdiagnosistoolbox/dmpermlib.cpython-313-x86_64-linux-gnu.so
faultdiagnosistoolbox/testselection_rf.py
faultdiagnosistoolbox/dmperm.py
faultdiagnosistoolbox/Matching.py
faultdiagnosistoolbox/CodeGeneration.py
faultdiagnosistoolbox/diag_util.py
faultdiagnosistoolbox/VarIdGen.py
faultdiagnosistoolbox/StructurePlotting.py
faultdiagnosistoolbox/models/_electric_motor_model.py
faultdiagnosistoolbox/models/__init__.py
faultdiagnosistoolbox/models/_three_tank_model.py
faultdiagnosistoolbox/models/_induction_motor_model.py
