Metadata-Version: 2.1
Name: faultdiagnosistoolbox
Version: 0.12.5
Summary: A toolbox for Model Based Fault Diagnosis of dynamic systems based on structural analysis
Author-Email: Erik Frisk <erik.frisk@liu.se>
Classifier: Programming Language :: Python :: 3
Classifier: License :: OSI Approved :: MIT License
Classifier: Development Status :: 4 - Beta
Classifier: Intended Audience :: Science/Research
Classifier: Topic :: Scientific/Engineering
Project-URL: Homepage, https://faultdiagnosistoolbox.github.io
Project-URL: Documentation, https://faultdiagnosistoolbox.readthedocs.io/
Project-URL: Issues, https://github.com/faultdiagnosistoolbox/pyfaultdiagnosistoolbox/issues
Project-URL: Repository, https://github.com/faultdiagnosistoolbox/pyfaultdiagnosistoolbox
Requires-Python: >=3.9
Requires-Dist: sympy
Requires-Dist: numpy
Requires-Dist: scipy
Requires-Dist: matplotlib
Requires-Dist: scikit-learn
